pystop/__init__.py
pystop/manifold/Euclidean.py
pystop/manifold/Product_manifold.py
pystop/manifold/Stiefel.py
pystop/manifold/__init__.py
pystop/solver/PenC.py
pystop/solver/PenCF.py
pystop/solver/SLPG.py
pystop/solver/__init__.py
pystop/utility/__init__.py
pystop/utility/pystop_autodiff.py
pystop/utility/utility.py
pystop-0.2.2.data/data/LICENSE
pystop-0.2.2.data/data/README.md
pystop-0.2.2.dist-info/METADATA
pystop-0.2.2.dist-info/RECORD
pystop-0.2.2.dist-info/WHEEL
pystop-0.2.2.dist-info/top_level.txt
