Metadata-Version: 2.1
Name: pystop
Version: 0.2.2
Summary: A Toolbox for Stiefel Manifold Optimization
Home-page: https://stmopt.gitee.io/
Author: Nachuan Xiao, Lei Wang, Bin Gao, Xin Liu, and Ya-xiang Yuan
Author-email: stmopt@foxmail.com
Keywords: optimization,manifold optimization,Stiefel manifold
Classifier: Programming Language :: Python :: 3
Classifier: Programming Language :: Python :: 3.7
Classifier: License :: OSI Approved :: GNU Lesser General Public License v3 or later (LGPLv3+)
Classifier: Operating System :: OS Independent
Requires-Python: >=3.6
License-File: LICENSE
Requires-Dist: numpy (>=1.16)
Requires-Dist: scipy
